pyhexedit/__init__.py
pyhexedit/pyhexedit.py
pyhexedit/stylehelper.py
pyhexedit/version.py
pyhexedit-1.0.1.dist-info/LICENSE
pyhexedit-1.0.1.dist-info/METADATA
pyhexedit-1.0.1.dist-info/WHEEL
pyhexedit-1.0.1.dist-info/top_level.txt
pyhexedit-1.0.1.dist-info/RECORD
