Metadata-Version: 2.1
Name: pyhexedit
Version: 1.0.1
Summary: Hex Editor
Home-page: https://github.com/timxx/pyhexedit
Author: Weitian Leung
Author-email: weitianleung@gmail.com
License: MIT
Keywords: hex editor pyside6 qt
Platform: any
Classifier: License :: OSI Approved :: MIT License
Classifier: Operating System :: POSIX
Classifier: Operating System :: POSIX :: BSD
Classifier: Operating System :: POSIX :: Linux
Classifier: Operating System :: Microsoft :: Windows
Classifier: Programming Language :: Python :: 3
Requires-Python: >=3
License-File: LICENSE
Requires-Dist: PySide6-Essentials >=6.3.0
